setup.cfg
setup.py
bin/maraithal
maraithal/__init__.py
maraithal/lsbstegano.py
maraithal.egg-info/PKG-INFO
maraithal.egg-info/SOURCES.txt
maraithal.egg-info/dependency_links.txt
maraithal.egg-info/pbr.json
maraithal.egg-info/requires.txt
maraithal.egg-info/top_level.txt