Metadata-Version: 1.1
Name: maraithal
Version: 0.5
Summary: Implementation of LSB Steganography to hide texts in images
Home-page: https://github.com/rkrp/maraithal
Author: Krishna Ram Prakash R
Author-email: krp@gtux.in
License: GPLv3
Download-URL: https://github.com/rkrp/maraithal
Platform: UNKNOWN
